{"nodes": [{"id": "ex00_scalarconverter_hpp", "label": "ScalarConverter.hpp", "file_type": "code", "source_file": "/home/rbagin/cpp_42/cpp_06/ex00/ScalarConverter.hpp", "source_location": null, "source_url": null, "captured_at": null, "author": null, "contributor": null}, {"id": "ex00_scalarconverter_class", "label": "ScalarConverter", "file_type": "code", "source_file": "/home/rbagin/cpp_42/cpp_06/ex00/ScalarConverter.hpp", "source_location": null, "source_url": null, "captured_at": null, "author": null, "contributor": null}, {"id": "ex00_literaltype_enum", "label": "LiteralType enum", "file_type": "code", "source_file": "/home/rbagin/cpp_42/cpp_06/ex00/ScalarConverter.hpp", "source_location": null, "source_url": null, "captured_at": null, "author": null, "contributor": null}], "edges": [], "hyperedges": []}