{"nodes": [{"id": "home_rbagin_cpp_42_cpp_00_ex01_phonebook_cpp", "label": "PhoneBook.cpp", "file_type": "code", "source_file": "/home/rbagin/cpp_42/cpp_00/ex01/PhoneBook.cpp", "source_location": "L1"}, {"id": "ex01_phonebook_phonebook", "label": "PhoneBook()", "file_type": "code", "source_file": "/home/rbagin/cpp_42/cpp_00/ex01/PhoneBook.cpp", "source_location": "L17"}, {"id": "ex01_phonebook_addcontact", "label": "addContact()", "file_type": "code", "source_file": "/home/rbagin/cpp_42/cpp_00/ex01/PhoneBook.cpp", "source_location": "L25"}, {"id": "ex01_phonebook_truncate", "label": "_truncate()", "file_type": "code", "source_file": "/home/rbagin/cpp_42/cpp_00/ex01/PhoneBook.cpp", "source_location": "L65"}, {"id": "ex01_phonebook_displaycontact", "label": "_displayContact()", "file_type": "code", "source_file": "/home/rbagin/cpp_42/cpp_00/ex01/PhoneBook.cpp", "source_location": "L71"}, {"id": "ex01_phonebook_displaytable", "label": "_displayTable()", "file_type": "code", "source_file": "/home/rbagin/cpp_42/cpp_00/ex01/PhoneBook.cpp", "source_location": "L81"}, {"id": "ex01_phonebook_searchcontact", "label": "searchContact()", "file_type": "code", "source_file": "/home/rbagin/cpp_42/cpp_00/ex01/PhoneBook.cpp", "source_location": "L96"}], "edges": [{"source": "home_rbagin_cpp_42_cpp_00_ex01_phonebook_cpp", "target": "home_rbagin_cpp_42_cpp_00_ex01_phonebook_hpp", "relation": "imports", "context": "import", "confidence": "EXTRACTED", "source_file": "/home/rbagin/cpp_42/cpp_00/ex01/PhoneBook.cpp", "source_location": "L13", "weight": 1.0}, {"source": "home_rbagin_cpp_42_cpp_00_ex01_phonebook_cpp", "target": "iostream", "relation": "imports", "context": "import", "confidence": "EXTRACTED", "source_file": "/home/rbagin/cpp_42/cpp_00/ex01/PhoneBook.cpp", "source_location": "L14", "weight": 1.0}, {"source": "home_rbagin_cpp_42_cpp_00_ex01_phonebook_cpp", "target": "iomanip", "relation": "imports", "context": "import", "confidence": "EXTRACTED", "source_file": "/home/rbagin/cpp_42/cpp_00/ex01/PhoneBook.cpp", "source_location": "L15", "weight": 1.0}, {"source": "home_rbagin_cpp_42_cpp_00_ex01_phonebook_cpp", "target": "ex01_phonebook_phonebook", "relation": "contains", "confidence": "EXTRACTED", "source_file": "/home/rbagin/cpp_42/cpp_00/ex01/PhoneBook.cpp", "source_location": "L17", "weight": 1.0}, {"source": "home_rbagin_cpp_42_cpp_00_ex01_phonebook_cpp", "target": "ex01_phonebook_phonebook", "relation": "contains", "confidence": "EXTRACTED", "source_file": "/home/rbagin/cpp_42/cpp_00/ex01/PhoneBook.cpp", "source_location": "L22", "weight": 1.0}, {"source": "home_rbagin_cpp_42_cpp_00_ex01_phonebook_cpp", "target": "ex01_phonebook_addcontact", "relation": "contains", "confidence": "EXTRACTED", "source_file": "/home/rbagin/cpp_42/cpp_00/ex01/PhoneBook.cpp", "source_location": "L25", "weight": 1.0}, {"source": "home_rbagin_cpp_42_cpp_00_ex01_phonebook_cpp", "target": "ex01_phonebook_truncate", "relation": "contains", "confidence": "EXTRACTED", "source_file": "/home/rbagin/cpp_42/cpp_00/ex01/PhoneBook.cpp", "source_location": "L65", "weight": 1.0}, {"source": "home_rbagin_cpp_42_cpp_00_ex01_phonebook_cpp", "target": "ex01_phonebook_displaycontact", "relation": "contains", "confidence": "EXTRACTED", "source_file": "/home/rbagin/cpp_42/cpp_00/ex01/PhoneBook.cpp", "source_location": "L71", "weight": 1.0}, {"source": "home_rbagin_cpp_42_cpp_00_ex01_phonebook_cpp", "target": "ex01_phonebook_displaytable", "relation": "contains", "confidence": "EXTRACTED", "source_file": "/home/rbagin/cpp_42/cpp_00/ex01/PhoneBook.cpp", "source_location": "L81", "weight": 1.0}, {"source": "home_rbagin_cpp_42_cpp_00_ex01_phonebook_cpp", "target": "ex01_phonebook_searchcontact", "relation": "contains", "confidence": "EXTRACTED", "source_file": "/home/rbagin/cpp_42/cpp_00/ex01/PhoneBook.cpp", "source_location": "L96", "weight": 1.0}, {"source": "ex01_phonebook_displaytable", "target": "ex01_phonebook_truncate", "relation": "calls", "context": "call", "confidence": "EXTRACTED", "source_file": "/home/rbagin/cpp_42/cpp_00/ex01/PhoneBook.cpp", "source_location": "L90", "weight": 1.0}, {"source": "ex01_phonebook_searchcontact", "target": "ex01_phonebook_displaytable", "relation": "calls", "context": "call", "confidence": "EXTRACTED", "source_file": "/home/rbagin/cpp_42/cpp_00/ex01/PhoneBook.cpp", "source_location": "L105", "weight": 1.0}, {"source": "ex01_phonebook_searchcontact", "target": "ex01_phonebook_displaycontact", "relation": "calls", "context": "call", "confidence": "EXTRACTED", "source_file": "/home/rbagin/cpp_42/cpp_00/ex01/PhoneBook.cpp", "source_location": "L115", "weight": 1.0}], "raw_calls": [{"caller_nid": "ex01_phonebook_addcontact", "callee": "getline", "is_member_call": true, "source_file": "/home/rbagin/cpp_42/cpp_00/ex01/PhoneBook.cpp", "source_location": "L29"}, {"caller_nid": "ex01_phonebook_addcontact", "callee": "eof", "is_member_call": true, "source_file": "/home/rbagin/cpp_42/cpp_00/ex01/PhoneBook.cpp", "source_location": "L30"}, {"caller_nid": "ex01_phonebook_addcontact", "callee": "empty", "is_member_call": true, "source_file": "/home/rbagin/cpp_42/cpp_00/ex01/PhoneBook.cpp", "source_location": "L30"}, {"caller_nid": "ex01_phonebook_addcontact", "callee": "setFirstName", "is_member_call": true, "source_file": "/home/rbagin/cpp_42/cpp_00/ex01/PhoneBook.cpp", "source_location": "L32"}, {"caller_nid": "ex01_phonebook_addcontact", "callee": "getline", "is_member_call": true, "source_file": "/home/rbagin/cpp_42/cpp_00/ex01/PhoneBook.cpp", "source_location": "L35"}, {"caller_nid": "ex01_phonebook_addcontact", "callee": "eof", "is_member_call": true, "source_file": "/home/rbagin/cpp_42/cpp_00/ex01/PhoneBook.cpp", "source_location": "L36"}, {"caller_nid": "ex01_phonebook_addcontact", "callee": "empty", "is_member_call": true, "source_file": "/home/rbagin/cpp_42/cpp_00/ex01/PhoneBook.cpp", "source_location": "L36"}, {"caller_nid": "ex01_phonebook_addcontact", "callee": "setLastName", "is_member_call": true, "source_file": "/home/rbagin/cpp_42/cpp_00/ex01/PhoneBook.cpp", "source_location": "L38"}, {"caller_nid": "ex01_phonebook_addcontact", "callee": "getline", "is_member_call": true, "source_file": "/home/rbagin/cpp_42/cpp_00/ex01/PhoneBook.cpp", "source_location": "L41"}, {"caller_nid": "ex01_phonebook_addcontact", "callee": "eof", "is_member_call": true, "source_file": "/home/rbagin/cpp_42/cpp_00/ex01/PhoneBook.cpp", "source_location": "L42"}, {"caller_nid": "ex01_phonebook_addcontact", "callee": "empty", "is_member_call": true, "source_file": "/home/rbagin/cpp_42/cpp_00/ex01/PhoneBook.cpp", "source_location": "L42"}, {"caller_nid": "ex01_phonebook_addcontact", "callee": "setNickname", "is_member_call": true, "source_file": "/home/rbagin/cpp_42/cpp_00/ex01/PhoneBook.cpp", "source_location": "L44"}, {"caller_nid": "ex01_phonebook_addcontact", "callee": "getline", "is_member_call": true, "source_file": "/home/rbagin/cpp_42/cpp_00/ex01/PhoneBook.cpp", "source_location": "L47"}, {"caller_nid": "ex01_phonebook_addcontact", "callee": "eof", "is_member_call": true, "source_file": "/home/rbagin/cpp_42/cpp_00/ex01/PhoneBook.cpp", "source_location": "L48"}, {"caller_nid": "ex01_phonebook_addcontact", "callee": "empty", "is_member_call": true, "source_file": "/home/rbagin/cpp_42/cpp_00/ex01/PhoneBook.cpp", "source_location": "L48"}, {"caller_nid": "ex01_phonebook_addcontact", "callee": "setPhoneNumber", "is_member_call": true, "source_file": "/home/rbagin/cpp_42/cpp_00/ex01/PhoneBook.cpp", "source_location": "L50"}, {"caller_nid": "ex01_phonebook_addcontact", "callee": "getline", "is_member_call": true, "source_file": "/home/rbagin/cpp_42/cpp_00/ex01/PhoneBook.cpp", "source_location": "L53"}, {"caller_nid": "ex01_phonebook_addcontact", "callee": "eof", "is_member_call": true, "source_file": "/home/rbagin/cpp_42/cpp_00/ex01/PhoneBook.cpp", "source_location": "L54"}, {"caller_nid": "ex01_phonebook_addcontact", "callee": "empty", "is_member_call": true, "source_file": "/home/rbagin/cpp_42/cpp_00/ex01/PhoneBook.cpp", "source_location": "L54"}, {"caller_nid": "ex01_phonebook_addcontact", "callee": "setDarkestSecret", "is_member_call": true, "source_file": "/home/rbagin/cpp_42/cpp_00/ex01/PhoneBook.cpp", "source_location": "L56"}, {"caller_nid": "ex01_phonebook_truncate", "callee": "length", "is_member_call": true, "source_file": "/home/rbagin/cpp_42/cpp_00/ex01/PhoneBook.cpp", "source_location": "L66"}, {"caller_nid": "ex01_phonebook_truncate", "callee": "substr", "is_member_call": true, "source_file": "/home/rbagin/cpp_42/cpp_00/ex01/PhoneBook.cpp", "source_location": "L67"}, {"caller_nid": "ex01_phonebook_displaycontact", "callee": "getFirstName", "is_member_call": true, "source_file": "/home/rbagin/cpp_42/cpp_00/ex01/PhoneBook.cpp", "source_location": "L73"}, {"caller_nid": "ex01_phonebook_displaycontact", "callee": "getLastName", "is_member_call": true, "source_file": "/home/rbagin/cpp_42/cpp_00/ex01/PhoneBook.cpp", "source_location": "L74"}, {"caller_nid": "ex01_phonebook_displaycontact", "callee": "getNickname", "is_member_call": true, "source_file": "/home/rbagin/cpp_42/cpp_00/ex01/PhoneBook.cpp", "source_location": "L75"}, {"caller_nid": "ex01_phonebook_displaycontact", "callee": "getPhoneNumber", "is_member_call": true, "source_file": "/home/rbagin/cpp_42/cpp_00/ex01/PhoneBook.cpp", "source_location": "L76"}, {"caller_nid": "ex01_phonebook_displaycontact", "callee": "getDarkestSecret", "is_member_call": true, "source_file": "/home/rbagin/cpp_42/cpp_00/ex01/PhoneBook.cpp", "source_location": "L77"}, {"caller_nid": "ex01_phonebook_displaytable", "callee": "setw", "is_member_call": true, "source_file": "/home/rbagin/cpp_42/cpp_00/ex01/PhoneBook.cpp", "source_location": "L82"}, {"caller_nid": "ex01_phonebook_displaytable", "callee": "setw", "is_member_call": true, "source_file": "/home/rbagin/cpp_42/cpp_00/ex01/PhoneBook.cpp", "source_location": "L83"}, {"caller_nid": "ex01_phonebook_displaytable", "callee": "setw", "is_member_call": true, "source_file": "/home/rbagin/cpp_42/cpp_00/ex01/PhoneBook.cpp", "source_location": "L84"}, {"caller_nid": "ex01_phonebook_displaytable", "callee": "setw", "is_member_call": true, "source_file": "/home/rbagin/cpp_42/cpp_00/ex01/PhoneBook.cpp", "source_location": "L85"}, {"caller_nid": "ex01_phonebook_displaytable", "callee": "setw", "is_member_call": true, "source_file": "/home/rbagin/cpp_42/cpp_00/ex01/PhoneBook.cpp", "source_location": "L89"}, {"caller_nid": "ex01_phonebook_displaytable", "callee": "setw", "is_member_call": true, "source_file": "/home/rbagin/cpp_42/cpp_00/ex01/PhoneBook.cpp", "source_location": "L90"}, {"caller_nid": "ex01_phonebook_displaytable", "callee": "getFirstName", "is_member_call": true, "source_file": "/home/rbagin/cpp_42/cpp_00/ex01/PhoneBook.cpp", "source_location": "L90"}, {"caller_nid": "ex01_phonebook_displaytable", "callee": "setw", "is_member_call": true, "source_file": "/home/rbagin/cpp_42/cpp_00/ex01/PhoneBook.cpp", "source_location": "L91"}, {"caller_nid": "ex01_phonebook_displaytable", "callee": "getLastName", "is_member_call": true, "source_file": "/home/rbagin/cpp_42/cpp_00/ex01/PhoneBook.cpp", "source_location": "L91"}, {"caller_nid": "ex01_phonebook_displaytable", "callee": "setw", "is_member_call": true, "source_file": "/home/rbagin/cpp_42/cpp_00/ex01/PhoneBook.cpp", "source_location": "L92"}, {"caller_nid": "ex01_phonebook_displaytable", "callee": "getNickname", "is_member_call": true, "source_file": "/home/rbagin/cpp_42/cpp_00/ex01/PhoneBook.cpp", "source_location": "L92"}, {"caller_nid": "ex01_phonebook_searchcontact", "callee": "getline", "is_member_call": true, "source_file": "/home/rbagin/cpp_42/cpp_00/ex01/PhoneBook.cpp", "source_location": "L108"}, {"caller_nid": "ex01_phonebook_searchcontact", "callee": "eof", "is_member_call": true, "source_file": "/home/rbagin/cpp_42/cpp_00/ex01/PhoneBook.cpp", "source_location": "L109"}, {"caller_nid": "ex01_phonebook_searchcontact", "callee": "length", "is_member_call": true, "source_file": "/home/rbagin/cpp_42/cpp_00/ex01/PhoneBook.cpp", "source_location": "L112"}]}